DaNuoYi/__init__.py
DaNuoYi/global_config.py
DaNuoYi/main.py
DaNuoYi/deep_learning/__init__.py
DaNuoYi/deep_learning/prepare_runtime_materials.py
DaNuoYi/deep_learning/classifier/__init__.py
DaNuoYi/deep_learning/classifier/classifier_model.py
DaNuoYi/deep_learning/classifier/dataset_utils.py
DaNuoYi/deep_learning/classifier/dynamic_rnn.py
DaNuoYi/deep_learning/classifier/fitness_assigner.py
DaNuoYi/deep_learning/classifier/train_classifier.py
DaNuoYi/deep_learning/translator/__init__.py
DaNuoYi/deep_learning/translator/generate_translated_case.py
DaNuoYi/deep_learning/translator/split_translation_dataset.py
DaNuoYi/deep_learning/translator/train_translator.py
DaNuoYi/deep_learning/translator/translator.py
DaNuoYi/deep_learning/translator/config/__init__.py
DaNuoYi/deep_learning/word2vec/__init__.py
DaNuoYi/deep_learning/word2vec/word2vec.py
DaNuoYi/evolution/__init__.py
DaNuoYi/evolution/evolution.py
DaNuoYi/evolution/fuzz_utils.py
DaNuoYi/evolution/fuzzer.py
DaNuoYi/evolution/entity/__init__.py
DaNuoYi/evolution/entity/individual.py
DaNuoYi/evolution/entity/population.py
DaNuoYi/injection_utils/__init__.py
DaNuoYi/injection_utils/injection_generation.py
DaNuoYi/injection_utils/payload/__init__.py
DaNuoYi/injection_utils/payload/payload.py
DaNuoYi/injection_utils/payload/payload_dict.py
DaNuoYi/utils/__init__.py
DaNuoYi/utils/bypass.py
DaNuoYi/utils/file_utils.py
DaNuoYi/utils/logger.py
DaNuoYi/utils/net_utils.py
DaNuoYi-0.2.0.dist-info/METADATA
DaNuoYi-0.2.0.dist-info/WHEEL
DaNuoYi-0.2.0.dist-info/top_level.txt
DaNuoYi-0.2.0.dist-info/RECORD
