Metadata-Version: 2.1
Name: DaNuoYi
Version: 0.2.0
Summary: This package provide the interface to run multitask evolutionary injection generation
Home-page: https://github.com/yangheng95/DaNuoYi
Author: Heng, Yang
Author-email: yangheng@exeter.ac.uk
License: MIT
Platform: UNKNOWN
Requires-Python: >=3.8
Requires-Dist: opennmt-py (==2.1.2)
Requires-Dist: torchtext
Requires-Dist: findfile
Requires-Dist: autocuda
Requires-Dist: googledrivedownloader
Requires-Dist: torch
Requires-Dist: termcolor
Requires-Dist: tqdm
Requires-Dist: matplotlib
